python_gitlab_plus/__init__.py
python_gitlab_plus/gitlab_plus.py
python_gitlab_plus-1.0.8.dist-info/licenses/LICENSE
python_gitlab_plus-1.0.8.dist-info/METADATA
python_gitlab_plus-1.0.8.dist-info/WHEEL
python_gitlab_plus-1.0.8.dist-info/top_level.txt
python_gitlab_plus-1.0.8.dist-info/RECORD
