Metadata-Version: 2.4
Name: python-gitlab-plus
Version: 1.0.8
Summary: Enhanced Python GitLab client.
Author: Avi Zaguri
License: MIT
Project-URL: Homepage, https://github.com/aviz92/python-gitlab-plus
Project-URL: Repository, https://github.com/aviz92/python-gitlab-plus
Project-URL: Issues, https://github.com/aviz92/python-gitlab-plus/issues
Keywords: development,gitlab,api,client,python
Classifier: Development Status :: 4 - Beta
Classifier: Intended Audience :: Developers
Classifier: Programming Language :: Python :: 3.11
Classifier: Operating System :: OS Independent
Classifier: Topic :: System :: Logging
Requires-Python: >=3.11
License-File: LICENSE
Requires-Dist: custom-python-logger>=2.0.11
Requires-Dist: pre-commit>=4.5.0
Requires-Dist: pytest>=9.0.1
Requires-Dist: python-base-toolkit>=0.0.17
Requires-Dist: python-dotenv>=1.2.1
Requires-Dist: python-gitlab>=7.0.0
Requires-Dist: setuptools>=80.9.0
Requires-Dist: wheel>=0.45.1
Dynamic: license-file
